__init__.py
_types.py
exceptions.py
helpers.py
api/__init__.py
api/app.py
api/dependencies.py
api/flags_router.py
api/models.py
cli/__init__.py
cli/fake_data.py
clients/__init__.py
clients/mongo_db_client.py
domain/__init__.py
domain/flag.py
flagbit-0.1.2.dist-info/licenses/LICENSE
repo/__init__.py
repo/base.py
repo/doc_store.py
repo/fake_repo.py
services/__init__.py
services/flagbit.py
flagbit-0.1.2.dist-info/METADATA
flagbit-0.1.2.dist-info/WHEEL
flagbit-0.1.2.dist-info/top_level.txt
flagbit-0.1.2.dist-info/RECORD
