Metadata-Version: 2.4
Name: flagbit
Version: 0.1.2
Summary: A 🐍 open source package for flag management 🚩
Requires-Python: >=3.12
License-File: LICENSE
Requires-Dist: fastapi>=0.116.1
Requires-Dist: httpx>=0.28.1
Requires-Dist: jinja2>=3.1.6
Requires-Dist: loguru>=0.7.3
Requires-Dist: pydantic-settings>=2.10.1
Requires-Dist: pymongo>=4.14.1
Requires-Dist: pytz>=2025.2
Requires-Dist: sqlalchemy>=2.0.43
Requires-Dist: uvicorn>=0.35.0
Dynamic: license-file
